rustshed/__init__.py
rustshed/option_result.py
rustshed/option_shortcut.py
rustshed/panic.py
rustshed/py.typed
rustshed/result_shortcut.py
rustshed/to_option.py
rustshed/to_result.py
rustshed/typeguards.py
rustshed-0.5.0.dist-info/METADATA
rustshed-0.5.0.dist-info/LICENSE
rustshed-0.5.0.dist-info/WHEEL
rustshed-0.5.0.dist-info/RECORD
