Metadata-Version: 2.1
Name: rustshed
Version: 0.5.0
Summary: Rust types in Python.
Home-page: https://github.com/pawelrubin/rustshed
License: MIT
Keywords: rust,result,option
Author: Paweł Rubin
Author-email: pawelrubindev@gmail.com
Requires-Python: >=3.10,<4.0
Classifier: Development Status :: 3 - Alpha
Classifier: License :: OSI Approved :: MIT License
Classifier: Programming Language :: Python :: 3
Classifier: Programming Language :: Python :: 3.10
Classifier: Programming Language :: Python :: 3.11
Classifier: Programming Language :: Python :: 3.10
Classifier: Programming Language :: Python :: 3.11
Classifier: Programming Language :: Python :: Implementation :: CPython
Classifier: Typing :: Typed
Project-URL: Repository, https://github.com/pawelrubin/rustshed
